{
  "unversionedId": "sdk/events",
  "id": "sdk/events",
  "title": "Events",
  "description": "The captcha widget emits DOM events which allow you to write code that reacts to changes in the widget.",
  "source": "@site/docs/sdk/events.md",
  "sourceDirName": "sdk",
  "slug": "/sdk/events",
  "permalink": "/docs/sdk/events",
  "draft": false,
  "editUrl": "https://github.com/friendlycaptcha/friendly-docs/tree/main/docs/sdk/events.md",
  "tags": [],
  "version": "current",
  "sidebarPosition": 2,
  "frontMatter": {
    "sidebar_position": 2
  },
  "sidebar": "tutorialSidebar",
  "previous": {
    "title": "Configuration",
    "permalink": "/docs/sdk/configuration"
  },
  "next": {
    "title": "Lifecycle",
    "permalink": "/docs/sdk/lifecycle"
  }
}